README.md
setup.py
voobly/__init__.py
voobly.egg-info/PKG-INFO
voobly.egg-info/SOURCES.txt
voobly.egg-info/dependency_links.txt
voobly.egg-info/requires.txt
voobly.egg-info/top_level.txt
voobly/metadata/games.json
voobly/metadata/ladders.json