Metadata-Version: 1.1
Name: voobly
Version: 1.2.7
Summary: Python 3 API for Voobly, the gaming platform.
Home-page: https://github.com/happyleavesaoc/python-voobly/
Author: happyleaves
Author-email: happyleaves.tfr@gmail.com
License: MIT
Platform: UNKNOWN
Classifier: License :: OSI Approved :: MIT License
Classifier: Operating System :: OS Independent
Classifier: Programming Language :: Python :: 3
